plover_json_lazy/__init__.py
plover_json_lazy-0.0.1.dist-info/LICENSE
plover_json_lazy-0.0.1.dist-info/METADATA
plover_json_lazy-0.0.1.dist-info/WHEEL
plover_json_lazy-0.0.1.dist-info/entry_points.txt
plover_json_lazy-0.0.1.dist-info/top_level.txt
plover_json_lazy-0.0.1.dist-info/zip-safe
plover_json_lazy-0.0.1.dist-info/RECORD
